hooks/hook-go2_webrtc_driver.py
phosphobot/__init__.py
phosphobot/_version.py
phosphobot/ai_control.py
phosphobot/api_posthog.py
phosphobot/api_supabase.py
phosphobot/app.py
phosphobot/camera.py
phosphobot/configs.py
phosphobot/control_signal.py
phosphobot/leader_follower.py
phosphobot/main.py
phosphobot/py.typed
phosphobot/recorder.py
phosphobot/robot.py
phosphobot/sentry.py
phosphobot/telemetry.py
phosphobot/teleoperation.py
phosphobot/types.py
phosphobot/utils.py
phosphobot/agents/__init__.py
phosphobot/agents/client.py
phosphobot/agents/robot.py
phosphobot/agents/server.py
phosphobot/am/__init__.py
phosphobot/am/act.py
phosphobot/am/base.py
phosphobot/am/gr00t.py
phosphobot/am/pi0.py
phosphobot/endpoints/__init__.py
phosphobot/endpoints/auth.py
phosphobot/endpoints/camera.py
phosphobot/endpoints/chat.py
phosphobot/endpoints/control.py
phosphobot/endpoints/networking.py
phosphobot/endpoints/pages.py
phosphobot/endpoints/recording.py
phosphobot/endpoints/training.py
phosphobot/hardware/__init__.py
phosphobot/hardware/base.py
phosphobot/hardware/go2.py
phosphobot/hardware/koch11.py
phosphobot/hardware/lekiwi.py
phosphobot/hardware/phosphobot.py
phosphobot/hardware/piper.py
phosphobot/hardware/sim.py
phosphobot/hardware/so100.py
phosphobot/hardware/wx250s.py
phosphobot/hardware/motors/__init__.py
phosphobot/hardware/motors/dynamixel.py
phosphobot/hardware/motors/feetech.py
phosphobot/hardware/motors/local_test.py
phosphobot/hardware/motors/motor_utils.py
phosphobot/hardware/motors/utils.py
phosphobot/models/__init__.py
phosphobot/models/camera.py
phosphobot/models/dataset.py
phosphobot/models/lerobot_dataset.py
phosphobot/models/robot.py
phosphobot/workaround/db.py
resources/.gitignore
resources/agilex_can_activate.sh
resources/tokens.toml
resources/calibration/koch-v1.1_58CD176940_config.json
resources/calibration/so-100_12V_config.json
resources/calibration/so-100_58CD176683_config.json
resources/calibration/so-100_58FA081789_config.json
navrim_phosphobot-0.1.1.dist-info/METADATA
navrim_phosphobot-0.1.1.dist-info/WHEEL
navrim_phosphobot-0.1.1.dist-info/entry_points.txt
navrim_phosphobot-0.1.1.dist-info/top_level.txt
navrim_phosphobot-0.1.1.dist-info/RECORD
