Metadata-Version: 2.4
Name: navrim-phosphobot
Version: 0.1.1
Summary: The AI-ready robotics dev kit, with built-in remote control and VLA support.
Author-email: navrim <contact@navrim.com>
License-Expression: MIT
Requires-Python: >=3.10
Requires-Dist: dynamixel-sdk>=3.7.31
Requires-Dist: fastapi[standard]>=0.115.5
Requires-Dist: loguru>=0.7.2
Requires-Dist: rich>=13.9.4
Requires-Dist: matplotlib>=3.9.3
Requires-Dist: numpy
Requires-Dist: pydantic>=2.10.2
Requires-Dist: scipy>=1.14.1
Requires-Dist: uvicorn>=0.32.1
Requires-Dist: opencv-python-headless>=4.0
Requires-Dist: requests>=2.32.4
Requires-Dist: types-requests>=2.32.0.20241016
Requires-Dist: json-numpy>=2.1.0
Requires-Dist: pandas>=2.2
Requires-Dist: tqdm>=4.67.1
Requires-Dist: feetech-servo-sdk>=1.0.0
Requires-Dist: typer>=0.15.1
Requires-Dist: websockets>=14.1
Requires-Dist: huggingface-hub>=0.28.0
Requires-Dist: datasets>=3.2.0
Requires-Dist: sentry-sdk[fastapi]>=2.20.0
Requires-Dist: posthog>=3.11.0
Requires-Dist: piper-sdk>=0.1.16
Requires-Dist: supabase>=2.15.0
Requires-Dist: zmq>=0.0.0
Requires-Dist: toml>=0.10.2
Requires-Dist: av>=12.0.0
Requires-Dist: tyro>=0.9.20
Requires-Dist: types-toml>=0.10.8.20240310
Requires-Dist: pyrealsense2>=2.54; platform_system == "Linux"
Requires-Dist: pyrealsense2>=2.54; platform_system == "Windows"
Requires-Dist: pyrealsense2-macosx>=2.54; platform_system == "Darwin"
Requires-Dist: fastparquet>=2024.11.0
Requires-Dist: httpx[socks]>=0.28.1
Requires-Dist: go2-webrtc-connect>=0.2.0
Requires-Dist: scapy>=2.6.1
Requires-Dist: wasmtime>=33.0.0
Requires-Dist: async-property>=0.2.2
Requires-Dist: langchain-openai>=0.3.25
Requires-Dist: copilotkit>=0.1.51
Requires-Dist: psutil>=7.0.0
Requires-Dist: navrim-lerobot>=0.1.0
